pyrcentages/__init__.py
pyrcentages/pyrcentages.py
pyrcentages-1.9.dist-info/METADATA
pyrcentages-1.9.dist-info/WHEEL
pyrcentages-1.9.dist-info/top_level.txt
pyrcentages-1.9.dist-info/RECORD
